headlessvim/runtimepath.py
headlessvim/_version.py
headlessvim/arguments.py
headlessvim/__init__.py
headlessvim/process.py
headlessvim-0.0.5.dist-info/pbr.json
headlessvim-0.0.5.dist-info/METADATA
headlessvim-0.0.5.dist-info/WHEEL
headlessvim-0.0.5.dist-info/RECORD
headlessvim-0.0.5.dist-info/metadata.json
headlessvim-0.0.5.dist-info/top_level.txt
headlessvim-0.0.5.dist-info/DESCRIPTION.rst
