Metadata-Version: 2.0
Name: headlessvim
Version: 0.0.5
Summary: programmable Vim, no need of +clientserver!
Home-page: https://github.com/manicmaniac/headlessvim
Author: Ryosuke Ito
Author-email: rito.0305@gmail.com
License: MIT
Keywords: vim test
Platform: UNKNOWN
Classifier: Development Status :: 3 - Alpha
Classifier: Topic :: Software Development :: Testing
Classifier: Programming Language :: Python :: 2.6
Classifier: Programming Language :: Python :: 2.7
Classifier: Programming Language :: Python :: 3.2
Classifier: Programming Language :: Python :: 3.3
Classifier: Programming Language :: Python :: 3.4
Classifier: License :: OSI Approved :: MIT License
Requires-Dist: pyte (>=0.4.10)
Requires-Dist: six (>=1.9.0)
